fast_inverted_index-0.4.7.dist-info/METADATA
fast_inverted_index-0.4.7.dist-info/WHEEL
fast_inverted_index-0.4.7.dist-info/licenses/LICENSE
fast_inverted_index/__init__.py
fast_inverted_index/_fast_inverted_index.abi3.so
fast_inverted_index/examples/ARROW_INTEGRATION_README.md
fast_inverted_index/examples/INTEGRATION_INSTRUCTIONS.md
fast_inverted_index/examples/README.md
fast_inverted_index/examples/__init__.py
fast_inverted_index/examples/arrow_benchmark.py
fast_inverted_index/examples/arrow_benchmark_new.py
fast_inverted_index/examples/arrow_comparison_benchmark.py
fast_inverted_index/examples/arrow_comprehensive_test.py
fast_inverted_index/examples/arrow_example.py
fast_inverted_index/examples/arrow_findings.md
fast_inverted_index/examples/arrow_implementation_guide.md
fast_inverted_index/examples/arrow_native_api.py
fast_inverted_index/examples/arrow_native_integration.py
fast_inverted_index/examples/arrow_optimized_benchmark.py
fast_inverted_index/examples/arrow_parallel_example.py
fast_inverted_index/examples/arrow_production_test.py
fast_inverted_index/examples/arrow_profile.py
fast_inverted_index/examples/arrow_simple_benchmark.py
fast_inverted_index/examples/arrow_test.py
fast_inverted_index/examples/content_retrieval.py
fast_inverted_index/examples/field_search_example.py
fast_inverted_index/examples/fix_benchmark.py
fast_inverted_index/examples/index/000035.sst
fast_inverted_index/examples/index/000053.sst
fast_inverted_index/examples/index/000087.sst
fast_inverted_index/examples/index/000090.sst
fast_inverted_index/examples/index/000110.log
fast_inverted_index/examples/index/000114.sst
fast_inverted_index/examples/index/000115.sst
fast_inverted_index/examples/index/000116.sst
fast_inverted_index/examples/index/CURRENT
fast_inverted_index/examples/index/IDENTITY
fast_inverted_index/examples/index/LOCK
fast_inverted_index/examples/index/LOG
fast_inverted_index/examples/index/LOG.old.1747084258272504
fast_inverted_index/examples/index/LOG.old.1747084752395748
fast_inverted_index/examples/index/LOG.old.1747084763857998
fast_inverted_index/examples/index/LOG.old.1747084766400972
fast_inverted_index-0.4.7.dist-info/RECORD
