Metadata-Version: 2.4
Name: fast_inverted_index
Version: 0.4.7
Classifier: Programming Language :: Rust
Classifier: Programming Language :: Python :: Implementation :: CPython
Classifier: Programming Language :: Python :: 3.8
Classifier: Programming Language :: Python :: 3.9
Classifier: Programming Language :: Python :: 3.10
Classifier: Programming Language :: Python :: 3.11
Classifier: Programming Language :: Python :: 3.12
Classifier: Typing :: Typed
License-File: LICENSE
Summary: High-performance inverted index for search engines
Author: Lakshmi Narasimman, Gideon Philip
License: MIT
Requires-Python: >=3.8
Project-URL: Source Code, https://github.com/gideonphilip/fast-inverted-index
